[{"mesh_num": 52, "filename": "alpha_sprites_font1_00.png", "x": 1, "y": 1, "w": 10, "h": 13, "l": 0, "t": -13, "b": 1, "r": 11}, {"mesh_num": 54, "filename": "alpha_sprites_font1_00.png", "x": 1, "y": 16, "w": 10, "h": 13, "l": 0, "t": -13, "b": 1, "r": 11}, {"mesh_num": 56, "filename": "alpha_sprites_font1_00.png", "x": 1, "y": 31, "w": 10, "h": 13, "l": 0, "t": -13, "b": 1, "r": 11}, {"mesh_num": 58, "filename": "alpha_sprites_font1_00.png", "x": 1, "y": 46, "w": 10, "h": 13, "l": 0, "t": -13, "b": 1, "r": 11}, {"mesh_num": 59, "filename": "alpha_sprites_font1_00.png", "x": 1, "y": 61, "w": 10, "h": 13, "l": 0, "t": -13, "b": 1, "r": 11}, {"mesh_num": 61, "filename": "alpha_sprites_font1_00.png", "x": 1, "y": 76, "w": 10, "h": 13, "l": 0, "t": -13, "b": 1, "r": 11}, {"mesh_num": 55, "filename": "alpha_sprites_font1_00.png", "x": 1, "y": 91, "w": 9, "h": 13, "l": 0, "t": -13, "b": 1, "r": 10}, {"mesh_num": 57, "filename": "alpha_sprites_font1_00.png", "x": 1, "y": 106, "w": 9, "h": 13, "l": 0, "t": -13, "b": 1, "r": 10}, {"mesh_num": 60, "filename": "alpha_sprites_font1_00.png", "x": 1, "y": 121, "w": 8, "h": 13, "l": 0, "t": -13, "b": 1, "r": 9}, {"mesh_num": 53, "filename": "alpha_sprites_font1_00.png", "x": 1, "y": 136, "w": 6, "h": 13, "l": 0, "t": -13, "b": 1, "r": 7}, {"mesh_num": 141, "filename": "alpha_sprites_font1_00.png", "x": 1, "y": 151, "w": 8, "h": 6, "l": 0, "t": -13, "b": -6, "r": 9}, {"mesh_num": 63, "filename": "alpha_sprites_font1_00.png", "x": 9, "y": 136, "w": 5, "h": 6, "l": 0, "t": -3, "b": 4, "r": 6}, {"mesh_num": 71, "filename": "alpha_sprites_font1_00.png", "x": 9, "y": 144, "w": 7, "h": 3, "l": 0, "t": -6, "b": -2, "r": 8}]